{
  "date_display": "2026-05-04 MON",
  "video_id": "_jjzGB_0gA0",
  "video_title": "한국경제신문 30분 만에 읽기 | 20260504🌞#모닝루틴",
  "items": [
    {
      "title": "버핏 \"요즘 미국증시 도박판 분위기 빠져\"",
      "content": "워런 버핏 전 벅셔해서웨이 CEO는 2일(현지시간) CNBC와 인터뷰에서 최근 미국 증시를 비판했다. 그는 하루짜리 옵션을 사고파는 것을 도박이라고 비판하며, 40만달러를 벌어들인 미군 병사의 사건을 언급했다. 워런 버핏은 투자하기 적절한 시기를 묻는 질문에 가격 하락 국면에 투자에 나설 수 있다고 답했다. 그는 벅셔해서웨이는 적절한 경영진을 갖추고 있으며 투자 타이밍을 선별할 수 있다고 덧붙였다. 워런 버핏은 과대 평가된 가격이 투자를 주저하게 하는 요인이라고 말했다.",
      "url": "https://www.hankyung.com/article/2026050328951"
    },
    {
      "title": "\"우리가 현금 인출기냐, 어디 잘해봐라\"…삼전노조 갈등 폭발",
      "content": "삼성전자 노조의 파업 예고에 대한 시장의 우려는 갈수록 커지고 있다. 최근 2500여명의 DX 부문 직원이 노조를 탈퇴하는 등 내부 반발이 커지고 있다. 이는 노조가 반도체 부문 직원의 이해관계를 우선시하고 다른 부문 직원들의 요구는 제대로 수용하지 않는다는 불만에서 비롯됐다. 특히 노조는 DS 부문 직원에게만 영업이익의 15%와 성과급 상한 영구 폐지를 요구하고 있어 대규모 성과급 충당금 설정이 단기 실적의 발목을 잡을 수 있다고 전한다. 씨티그룹은 이를 고려해 삼성전자 목표주가를 34만원에서 30만원으로 하향 조정했다.",
      "url": "https://www.hankyung.com/article/2026050329461"
    },
    {
      "title": "MZ들 열광한 '꽃무늬 티셔츠'…요즘 왜 안보이나 했더니 [장서우의 하입:hype]",
      "content": "마르디 메크르디의 1분기 매출은 약 234억원으로 1년 전 같은 기간보다 30% 감소했다. 같은 기간 판매·관리비 등을 차감한 영업이익은 80억원에서 20억원으로 75% 감소했다. 마르디 메크르디는 자사몰 직접 판매를 통해 플랫폼 수수료를 아끼려던 전략이 실패했다. 2023년 213억원이었던 판관비는 2025년 520억원으로 2년 만에 두 배 이상으로 증가했다. 마르디 메크르디의 이러한 실적 악화는 2023년 말 무신사와의 결별, '로고 플레이' 마케팅의 한계, 브랜드 확장에 대한 소홀함 등이 원인이었다.",
      "url": "https://www.hankyung.com/article/2026050328391"
    },
    {
      "title": "오늘의집도 돈 넣었다…리빙으로 번진 '무신사式 투자모델'",
      "content": "리빙·가구 브랜드에 잇달아 투자한 сегодня의집은 인테리어 생태계를 키우려는 전략을 세웠다. 3일 오늘의집 운영사 버킷플레이스 사업보고서에 따르면 악동뮤지션 이찬혁이 설립한 리빙 브랜드 기업 ‘투셰’에 28억원을 투자해 지분 80%를 확보했다. 지난해 철제가구로 유명한 가구 브랜드 ‘레어로우’에도 34억원을 투자해 지분 25%를 확보했다. 또한 커스텀 가구 브랜드 ‘에프피앤코’에는 2024년 20억원을 투자하고 지난 3월엔 지분을 60.5%로 늘렸다. 무신사도 투자 전문 자회사인 무신사파트너스를 통해 가구와 인테리어 브랜드 투자를 늘리고 있다.",
      "url": "https://www.hankyung.com/article/2026050328411"
    },
    {
      "title": "\"中마저 물량 없다\"…사상 초유 '동박의 난' 애타는 사장님",
      "content": "인공지능(AI) 반도체, 데이터센터, 자율주행 자동차 등의 수요로 인해 PCB 핵심 소재인 CCL 가격이 천정부지로 뛰고 있으며, 지난 3월 CCL 수입 단가는 2만728달러로 74.5% 상승했다. 이는 관련 통계를 작성하기 시작한 2000년 이후 처음이었다. CCL 공급난으로 인해 국내 중소 PCB 업체는 공장 가동을 멈춰야 하는 위기에 내몰렸으며, 일부 기업은 CCL 납품 일정을 앞당기기 위해 선박 대신 항공으로 제품을 운송하는 방안을 추진했다. 특히 두산의 주가는 2024년 4월 말 15만2300원에서 지난달 말 159만6000원으로 2년간 10배 이상으로 뛰었다. CCL 수출 단가도 급등하며, 지난달 평균 수출단가는 3만998달러로 1년 전보다 65.2% 급등했다.",
      "url": "https://www.hankyung.com/article/2026050329271"
    },
    {
      "title": "K전력기기 수출 훈풍에 'AI 전력 인프라' 고공행진",
      "content": "지난주 국내 전력기기 기업의 미국 수출이 견조한 흐름을 보이면서 관련 종목 주가를 끌어올렸다. 3일 ETF체크에 따르면 지난주 수익률이 가장 높았던 ETF는 ‘KODEX AI전력핵심설비’였다. 이 기간 16.58% 상승했다. 지난 3월 대형 변압기 미국 수출액은 9687만달러로 전년 동기 대비 121.4% 증가했다. 효성중공업은 지난주 장중 한때 400만원을 넘어서며 ‘슈퍼황제주’로 떠올랐고, 올해 누적 상승률은 110%를 넘어섰다.",
      "url": "https://www.hankyung.com/article/202605032647i"
    },
    {
      "title": "'반도체만 가란 법 있나'…소외주 5월에 '대반전' 노린다",
      "content": "한국거래소에 따르면 이날 코스피지수는 전일 대比 1.38% 내린 6598.87에 마감했다. 지난 3월 말(5052.46)과 비교하면 30.6% 높다. 상승장을 견인한 주역은 단연 반도체와 건설, 에너지였다. 한국거래소에 따르면 삼성전자, SK하이닉스, 삼성전기 등이 포함된 ‘KRX 정보기술지수’는 한 달간 상승률이 49.75%에 달했으며, 이에 비해 국내 증시 유동성은 여전히 풍부하다. 1월부터 4월까지 넉 달 연속 하루 평균 거래대금은 40조원을 웃돌았다.",
      "url": "https://www.hankyung.com/article/2026043095331"
    },
    {
      "title": "삼성바이오 노조 '재택 파업'…영업이익 20% 성과급 요구",
      "content": "삼성바이오로직스 노동조합이 1일 전면 파업에 들어갔으며, 회사 측에 따르면 전체 조합원 약 4000명 가운데 2500여 명이 파업에 동참했다. 이는 2011년 회사 설립 이후 첫 파업이다. 노조는 평균 14%의 임금 인상, 영업이익의 20% 초과이익성과급으로 지급 등을 요구했지만, 사측은 6.2% 인상안에서 물러서지 않았다. 존 림 대표는 파업을 하루 앞둔 지난달 30일 밤 임직원들에게 이메일을 보내 파업 철회를 호소했으며, 노조는 5일까지 파업을 이어갈 예정이다. 노조는 사측의 파업 참가 여부 사전 확인, 손실 규모를 앞세운 경고성 메시지 등으로 대응한 점을 비판했다.",
      "url": "https://www.hankyung.com/article/2026050110291"
    },
    {
      "title": "유증 2.4조→1.8조→?…한화솔루션, 더 줄일듯",
      "content": "금융감독원은 지난달 30일 한화솔루션의 유상증자 정정안에 대해 2차 정정신고서 제출을 요구했다. 이를 통해 한화솔루션이 유상증자 규모를 또다시 축소할 것이라는 전망이 나왔다. 한화솔루션은 지난 3월 2조3976억원 규모의 유상증자를 발표했으나 정정신고서를 통해 1조8144억원으로 축소했다. 금감원은 1차 심사 당시 한화솔루션이 유상증자의 필요성을 증권신고서에 충분히 기재하지 않았다고 판단했으며, 특히 5조원 상당의 비업무용 자산을 문제 삼았다. 한화솔루션은 1조8144억원의 유상증자액 중 채무상환 자금 용도가 9067억원으로 여전히 50%에 육박해, 추가적인 규모 축소가 예상된다.",
      "url": "https://www.hankyung.com/article/2026050110401"
    },
    {
      "title": "수집품 시장 확대에…게임스톱, 이베이 품나",
      "content": "수집품 시장은 동전과 만화책부터 기념품 등을 거래하는 분야인데, 크리스티와 소더비 등 대형 경매사들이 잇따라 뛰어들었다. 고가 낙찰 사례가 잇따르며 과거 소규모 딜러 중심이던 수집품 시장이 근본적으로 바뀐 데 따른 것이다. 월스트리트저널은 2일 게임스톱이 수집품 거래 시장에서의 시너지를 노리고 이베이 인수를 제안하는 방안을 준비 중이라고 보도했다. 이베이는 지난해 매출이 약 110억달러를 기록했으며, 순이익도 약 20억달러로 소폭 증가했다. 특히 이베이 주가는 지난 1년간 약 50% 상승했다.",
      "url": "https://www.hankyung.com/article/2026050328961"
    }
  ]
}